word_lexord/__init__.py
word_lexord/__main__.py
word_lexord/base.py
word_lexord/lang.py
wordlexord-0.0.2.dist-info/LICENSE
wordlexord-0.0.2.dist-info/METADATA
wordlexord-0.0.2.dist-info/WHEEL
wordlexord-0.0.2.dist-info/top_level.txt
wordlexord-0.0.2.dist-info/RECORD
