Metadata-Version: 2.1
Name: wordlexord
Version: 0.0.2
Summary: This is a python package for having fun with words ordered by length and then lexicographically
Home-page: https://github.com/lindy2076/words-serial-number
Download-URL: https://github.com/lindy2076/words-serial-number/issues
Author: Aleksej Kosolapov
Author-email: Aleksej Kosolapov <kakaporuqee@gmail.com>
License: MIT
Project-URL: Homepage, https://github.com/lindy2076/words-serial-number
Project-URL: Bug Tracker, https://github.com/lindy2076/words-serial-number/issues
Keywords: words,order,ordered,lexicographically
Classifier: Programming Language :: Python :: 3
Classifier: License :: OSI Approved :: MIT License
Classifier: Operating System :: Unix
Requires-Python: >=3.10
License-File: LICENSE
